CHANGES.txt
LICENSE.txt
MANIFEST.in
README.txt
setup.py
sk
serieskeeper/__init__.py
serieskeeper/data.py
serieskeeper/serieskeeper.py
serieskeeper.egg-info/PKG-INFO
serieskeeper.egg-info/SOURCES.txt
serieskeeper.egg-info/dependency_links.txt
serieskeeper.egg-info/top_level.txt