Metadata-Version: 1.1
Name: serieskeeper
Version: v0.0.0
Summary: Serieskeeper - Remember what you have started and finished
Home-page: https://bitbucket.org/cnodell/serieskeeper/overview
Author: Charles Nodell
Author-email: cnodell@simplesparks.com
License: UNKNOWN
Download-URL: https://bitbucket.org/cnodell/serieskeeper/downloads/
Platform: UNKNOWN
Classifier: Programming Language :: Python
Classifier: Development Status :: 3 - Alpha
Classifier: Environment :: Console
Classifier: Intended Audience :: End Users/Desktop
Classifier: License :: OSI Approved :: MIT License
Classifier: Operating System :: OS Independent
Classifier: Topic :: Other/Nonlisted Topic
